<?xml version="1.0"?>
<!DOCTYPE hibernate-mapping PUBLIC "-//Hibernate/Hibernate Mapping DTD 3.0//EN"
"http://www.hibernate.org/dtd/hibernate-mapping-3.0.dtd">
<!-- Generated May 11, 2016 1:11:25 PM by Hibernate Tools 4.3.1 -->
<hibernate-mapping>
    <class name="vn.edu.vnu.uet.fit.entity.Semesters" table="semesters" catalog="uetcodehub">
        <id name="semesterId" type="java.lang.Integer">
            <column name="semesterId" />
            <generator class="identity"></generator>
        </id>
        <property name="semesterName" type="string">
            <column name="semesterName" length="200" not-null="true" />
        </property>
    </class>
</hibernate-mapping>
